{"note":"This file is an internal implementation detail to speed up HTML report generation. Its format can change at any time. You might be looking for the JSON report: https://coverage.rtfd.io/cmd.html#cmd-json","format":5,"version":"7.6.10","globals":"ca304e0637693b1b8904f4264246857d","files":{"z_145eef247bfb46b6___init___py":{"hash":"e6baa73cda2916dad605215f937a92e1","index":{"url":"z_145eef247bfb46b6___init___py.html","file":"src\\__init__.py","description":"","nums":{"precision":0,"n_files":1,"n_statements":0,"n_excluded":0,"n_missing":0,"n_branches":0,"n_partial_branches":0,"n_missing_branches":0}}},"z_145eef247bfb46b6_category_py":{"hash":"0be940d0fbc6d916a3e6f4aa231f7008","index":{"url":"z_145eef247bfb46b6_category_py.html","file":"src\\category.py","description":"","nums":{"precision":0,"n_files":1,"n_statements":35,"n_excluded":0,"n_missing":0,"n_branches":0,"n_partial_branches":0,"n_missing_branches":0}}},"z_145eef247bfb46b6_product_py":{"hash":"f2fb68ce99902b340ca22b5fe9c276d6","index":{"url":"z_145eef247bfb46b6_product_py.html","file":"src\\product.py","description":"","nums":{"precision":0,"n_files":1,"n_statements":49,"n_excluded":0,"n_missing":0,"n_branches":0,"n_partial_branches":0,"n_missing_branches":0}}},"z_145eef247bfb46b6_utils_py":{"hash":"b6e01248498ce64e6bb73b2401d3fcdb","index":{"url":"z_145eef247bfb46b6_utils_py.html","file":"src\\utils.py","description":"","nums":{"precision":0,"n_files":1,"n_statements":17,"n_excluded":0,"n_missing":0,"n_branches":0,"n_partial_branches":0,"n_missing_branches":0}}},"z_145eef247bfb46b6_product_iterator_py":{"hash":"e34f4fbd357303369a9e7a48cdaab414","index":{"url":"z_145eef247bfb46b6_product_iterator_py.html","file":"src\\product_iterator.py","description":"","nums":{"precision":0,"n_files":1,"n_statements":15,"n_excluded":0,"n_missing":0,"n_branches":0,"n_partial_branches":0,"n_missing_branches":0}}},"z_145eef247bfb46b6_lawngrass_py":{"hash":"5aa74c733759b72fbb3468d099ec897d","index":{"url":"z_145eef247bfb46b6_lawngrass_py.html","file":"src\\lawngrass.py","description":"","nums":{"precision":0,"n_files":1,"n_statements":7,"n_excluded":0,"n_missing":0,"n_branches":0,"n_partial_branches":0,"n_missing_branches":0}}},"z_145eef247bfb46b6_smartphone_py":{"hash":"f6ce1ff452bc78cdc5824443c38d6f23","index":{"url":"z_145eef247bfb46b6_smartphone_py.html","file":"src\\smartphone.py","description":"","nums":{"precision":0,"n_files":1,"n_statements":8,"n_excluded":0,"n_missing":0,"n_branches":0,"n_partial_branches":0,"n_missing_branches":0}}}}}